{".class": "MypyFile", "_fullname": "git.objects.blob", "is_partial_stub_package": false, "is_stub": false, "names": {".class": "SymbolTable", "Blob": {".class": "SymbolTableNode", "kind": "Gdef", "node": {".class": "TypeInfo", "_promote": null, "abstract_attributes": [], "bases": ["git.objects.base.IndexObject"], "declared_metaclass": null, "defn": {".class": "ClassDef", "fullname": "git.objects.blob.Blob", "name": "Blob", "type_vars": []}, "flags": ["fallback_to_any"], "fullname": "git.objects.blob.Blob", "metaclass_type": null, "metadata": {}, "module_name": "git.objects.blob", "mro": ["git.objects.blob.Blob", "git.objects.base.IndexObject", "git.objects.base.Object", "builtins.object"], "names": {".class": "SymbolTable", "DEFAULT_MIME_TYPE": {".class": "SymbolTableNode", "kind": "Mdef", "node": {".class": "Var", "flags": ["is_initialized_in_class", "is_ready"], "fullname": "git.objects.blob.Blob.DEFAULT_MIME_TYPE", "name": "DEFAULT_MIME_TYPE", "type": "builtins.str"}}, "__slots__": {".class": "SymbolTableNode", "kind": "Mdef", "node": {".class": "Var", "flags": ["is_initialized_in_class"], "fullname": "git.objects.blob.Blob.__slots__", "name": "__slots__", "type": {".class": "TupleType", "implicit": false, "items": [], "partial_fallback": {".class": "Instance", "args": [{".class": "AnyType", "missing_import_name": null, "source_any": null, "type_of_any": 6}], "type_ref": "builtins.tuple"}}}}, "executable_mode": {".class": "SymbolTableNode", "kind": "Mdef", "node": {".class": "Var", "flags": ["is_initialized_in_class", "is_ready"], "fullname": "git.objects.blob.Blob.executable_mode", "name": "executable_mode", "type": "builtins.int"}}, "file_mode": {".class": "SymbolTableNode", "kind": "Mdef", "node": {".class": "Var", "flags": ["is_initialized_in_class", "is_ready"], "fullname": "git.objects.blob.Blob.file_mode", "name": "file_mode", "type": "builtins.int"}}, "link_mode": {".class": "SymbolTableNode", "kind": "Mdef", "node": {".class": "Var", "flags": ["is_initialized_in_class", "is_ready"], "fullname": "git.objects.blob.Blob.link_mode", "name": "link_mode", "type": "builtins.int"}}, "mime_type": {".class": "SymbolTableNode", "kind": "Mdef", "node": {".class": "Decorator", "func": {".class": "FuncDef", "arg_kinds": [0], "arg_names": ["self"], "flags": ["is_property", "is_decorated"], "fullname": "git.objects.blob.Blob.mime_type", "name": "mime_type", "type": null}, "is_overload": false, "var": {".class": "Var", "flags": ["is_initialized_in_class", "is_property", "is_ready"], "fullname": null, "name": "mime_type", "type": {".class": "CallableType", "arg_kinds": [0], "arg_names": ["self"], "arg_types": ["git.objects.blob.Blob"], "bound_args": [], "def_extras": {}, "fallback": "builtins.function", "implicit": true, "is_ellipsis_args": false, "name": "mime_type of Blob", "ret_type": {".class": "AnyType", "missing_import_name": null, "source_any": null, "type_of_any": 1}, "variables": []}}}}, "type": {".class": "SymbolTableNode", "kind": "Mdef", "node": {".class": "Var", "flags": ["is_initialized_in_class", "is_ready"], "fullname": "git.objects.blob.Blob.type", "name": "type", "type": "builtins.str"}}}, "tuple_type": null, "type_vars": [], "typeddict_type": null}}, "__all__": {".class": "SymbolTableNode", "kind": "Gdef", "module_public": false, "node": {".class": "Var", "flags": [], "fullname": "git.objects.blob.__all__", "name": "__all__", "type": {".class": "TupleType", "implicit": false, "items": ["builtins.str"], "partial_fallback": {".class": "Instance", "args": [{".class": "AnyType", "missing_import_name": null, "source_any": null, "type_of_any": 6}], "type_ref": "builtins.tuple"}}}}, "__doc__": {".class": "SymbolTableNode", "kind": "Gdef", "module_public": false, "node": {".class": "Var", "flags": ["is_ready"], "fullname": "git.objects.blob.__doc__", "name": "__doc__", "type": "builtins.str"}}, "__file__": {".class": "SymbolTableNode", "kind": "Gdef", "module_public": false, "node": {".class": "Var", "flags": ["is_ready"], "fullname": "git.objects.blob.__file__", "name": "__file__", "type": "builtins.str"}}, "__name__": {".class": "SymbolTableNode", "kind": "Gdef", "module_public": false, "node": {".class": "Var", "flags": ["is_ready"], "fullname": "git.objects.blob.__name__", "name": "__name__", "type": "builtins.str"}}, "__package__": {".class": "SymbolTableNode", "kind": "Gdef", "module_public": false, "node": {".class": "Var", "flags": ["is_ready"], "fullname": "git.objects.blob.__package__", "name": "__package__", "type": "builtins.str"}}, "base": {".class": "SymbolTableNode", "cross_ref": "git.objects.base", "kind": "Gdef", "module_public": false}, "guess_type": {".class": "SymbolTableNode", "cross_ref": "mimetypes.guess_type", "kind": "Gdef", "module_public": false}}, "path": "c:\\dev\\GitPython\\git\\objects\\blob.py"}