{".class": "MypyFile", "_fullname": "git.objects.commit", "is_partial_stub_package": false, "is_stub": false, "names": {".class": "SymbolTable", "Actor": {".class": "SymbolTableNode", "cross_ref": "git.util.Actor", "kind": "Gdef", "module_public": false}, "BytesIO": {".class": "SymbolTableNode", "cross_ref": "io.BytesIO", "kind": "Gdef", "module_public": false}, "Commit": {".class": "SymbolTableNode", "kind": "Gdef", "node": {".class": "TypeInfo", "_promote": null, "abstract_attributes": [], "bases": ["git.objects.base.Object", "git.util.Iterable", "git.diff.Diffable", "git.objects.util.Traversable", "git.objects.util.Serializable"], "declared_metaclass": null, "defn": {".class": "ClassDef", "fullname": "git.objects.commit.Commit", "name": "Commit", "type_vars": []}, "flags": ["fallback_to_any"], "fullname": "git.objects.commit.Commit", "metaclass_type": null, "metadata": {}, "module_name": "git.objects.commit", "mro": ["git.objects.commit.Commit", "git.objects.base.Object", "git.util.Iterable", "git.diff.Diffable", "git.objects.util.Traversable", "git.objects.util.Serializable", "builtins.object"], "names": {".class": "SymbolTable", "__init__": {".class": "SymbolTableNode", "kind": "Mdef", "node": {".class": "FuncDef", "arg_kinds": [0, 0, 0, 1, 1, 1, 1, 1, 1, 1, 1, 1, 1, 1], "arg_names": ["self", "repo", "binsha", "tree", "author", "authored_date", "author_tz_offset", "committer", "committed_date", "committer_tz_offset", "message", "parents", "encoding", "gpgsig"], "flags": [], "fullname": "git.objects.commit.Commit.__init__", "name": "__init__", "type": null}}, "__slots__": {".class": "SymbolTableNode", "kind": "Mdef", "node": {".class": "Var", "flags": ["is_initialized_in_class"], "fullname": "git.objects.commit.Commit.__slots__", "name": "__slots__", "type": {".class": "TupleType", "implicit": false, "items": ["builtins.str", "builtins.str", "builtins.str", "builtins.str", "builtins.str", "builtins.str", "builtins.str", "builtins.str", "builtins.str", "builtins.str", "builtins.str"], "partial_fallback": {".class": "Instance", "args": [{".class": "AnyType", "missing_import_name": null, "source_any": null, "type_of_any": 6}], "type_ref": "builtins.tuple"}}}}, "_calculate_sha_": {".class": "SymbolTableNode", "kind": "Mdef", "node": {".class": "Decorator", "func": {".class": "FuncDef", "arg_kinds": [0, 0, 0], "arg_names": ["cls", "repo", "commit"], "flags": ["is_class", "is_decorated"], "fullname": "git.objects.commit.Commit._calculate_sha_", "name": "_calculate_sha_", "type": null}, "is_overload": false, "var": {".class": "Var", "flags": ["is_initialized_in_class", "is_classmethod", "is_ready"], "fullname": null, "name": "_calculate_sha_", "type": {".class": "CallableType", "arg_kinds": [0, 0, 0], "arg_names": ["cls", "repo", "commit"], "arg_types": [{".class": "TypeType", "item": "git.objects.commit.Commit"}, {".class": "AnyType", "missing_import_name": null, "source_any": null, "type_of_any": 1}, {".class": "AnyType", "missing_import_name": null, "source_any": null, "type_of_any": 1}], "bound_args": [], "def_extras": {}, "fallback": "builtins.function", "implicit": true, "is_ellipsis_args": false, "name": "_calculate_sha_ of Commit", "ret_type": {".class": "AnyType", "missing_import_name": null, "source_any": null, "type_of_any": 1}, "variables": []}}}}, "_deserialize": {".class": "SymbolTableNode", "kind": "Mdef", "node": {".class": "FuncDef", "arg_kinds": [0, 0], "arg_names": ["self", "stream"], "flags": [], "fullname": "git.objects.commit.Commit._deserialize", "name": "_deserialize", "type": null}}, "_get_intermediate_items": {".class": "SymbolTableNode", "kind": "Mdef", "node": {".class": "Decorator", "func": {".class": "FuncDef", "arg_kinds": [0, 0], "arg_names": ["cls", "commit"], "flags": ["is_class", "is_decorated"], "fullname": "git.objects.commit.Commit._get_intermediate_items", "name": "_get_intermediate_items", "type": null}, "is_overload": false, "var": {".class": "Var", "flags": ["is_initialized_in_class", "is_classmethod", "is_ready"], "fullname": null, "name": "_get_intermediate_items", "type": {".class": "CallableType", "arg_kinds": [0, 0], "arg_names": ["cls", "commit"], "arg_types": [{".class": "TypeType", "item": "git.objects.commit.Commit"}, {".class": "AnyType", "missing_import_name": null, "source_any": null, "type_of_any": 1}], "bound_args": [], "def_extras": {}, "fallback": "builtins.function", "implicit": true, "is_ellipsis_args": false, "name": "_get_intermediate_items of Commit", "ret_type": {".class": "AnyType", "missing_import_name": null, "source_any": null, "type_of_any": 1}, "variables": []}}}}, "_id_attribute_": {".class": "SymbolTableNode", "kind": "Mdef", "node": {".class": "Var", "flags": ["is_initialized_in_class", "is_ready"], "fullname": "git.objects.commit.Commit._id_attribute_", "name": "_id_attribute_", "type": "builtins.str"}}, "_iter_from_process_or_stream": {".class": "SymbolTableNode", "kind": "Mdef", "node": {".class": "Decorator", "func": {".class": "FuncDef", "arg_kinds": [0, 0, 0], "arg_names": ["cls", "repo", "proc_or_stream"], "flags": ["is_class", "is_generator", "is_decorated"], "fullname": "git.objects.commit.Commit._iter_from_process_or_stream", "name": "_iter_from_process_or_stream", "type": null}, "is_overload": false, "var": {".class": "Var", "flags": ["is_initialized_in_class", "is_classmethod", "is_ready"], "fullname": null, "name": "_iter_from_process_or_stream", "type": {".class": "CallableType", "arg_kinds": [0, 0, 0], "arg_names": ["cls", "repo", "proc_or_stream"], "arg_types": [{".class": "TypeType", "item": "git.objects.commit.Commit"}, {".class": "AnyType", "missing_import_name": null, "source_any": null, "type_of_any": 1}, {".class": "AnyType", "missing_import_name": null, "source_any": null, "type_of_any": 1}], "bound_args": [], "def_extras": {}, "fallback": "builtins.function", "implicit": true, "is_ellipsis_args": false, "name": "_iter_from_process_or_stream of Commit", "ret_type": {".class": "AnyType", "missing_import_name": null, "source_any": null, "type_of_any": 1}, "variables": []}}}}, "_serialize": {".class": "SymbolTableNode", "kind": "Mdef", "node": {".class": "FuncDef", "arg_kinds": [0, 0], "arg_names": ["self", "stream"], "flags": [], "fullname": "git.objects.commit.Commit._serialize", "name": "_serialize", "type": null}}, "_set_cache_": {".class": "SymbolTableNode", "kind": "Mdef", "node": {".class": "FuncDef", "arg_kinds": [0, 0], "arg_names": ["self", "attr"], "flags": [], "fullname": "git.objects.commit.Commit._set_cache_", "name": "_set_cache_", "type": null}}, "author": {".class": "SymbolTableNode", "implicit": true, "kind": "Mdef", "node": {".class": "Var", "flags": [], "fullname": "git.objects.commit.Commit.author", "name": "author", "type": {".class": "AnyType", "missing_import_name": null, "source_any": null, "type_of_any": 1}}}, "author_tz_offset": {".class": "SymbolTableNode", "implicit": true, "kind": "Mdef", "node": {".class": "Var", "flags": [], "fullname": "git.objects.commit.Commit.author_tz_offset", "name": "author_tz_offset", "type": {".class": "AnyType", "missing_import_name": null, "source_any": null, "type_of_any": 1}}}, "authored_date": {".class": "SymbolTableNode", "implicit": true, "kind": "Mdef", "node": {".class": "Var", "flags": [], "fullname": "git.objects.commit.Commit.authored_date", "name": "authored_date", "type": {".class": "AnyType", "missing_import_name": null, "source_any": null, "type_of_any": 1}}}, "authored_datetime": {".class": "SymbolTableNode", "kind": "Mdef", "node": {".class": "Decorator", "func": {".class": "FuncDef", "arg_kinds": [0], "arg_names": ["self"], "flags": ["is_property", "is_decorated"], "fullname": "git.objects.commit.Commit.authored_datetime", "name": "authored_datetime", "type": null}, "is_overload": false, "var": {".class": "Var", "flags": ["is_initialized_in_class", "is_property", "is_ready"], "fullname": null, "name": "authored_datetime", "type": {".class": "CallableType", "arg_kinds": [0], "arg_names": ["self"], "arg_types": ["git.objects.commit.Commit"], "bound_args": [], "def_extras": {}, "fallback": "builtins.function", "implicit": true, "is_ellipsis_args": false, "name": "authored_datetime of Commit", "ret_type": {".class": "AnyType", "missing_import_name": null, "source_any": null, "type_of_any": 1}, "variables": []}}}}, "committed_date": {".class": "SymbolTableNode", "implicit": true, "kind": "Mdef", "node": {".class": "Var", "flags": [], "fullname": "git.objects.commit.Commit.committed_date", "name": "committed_date", "type": {".class": "AnyType", "missing_import_name": null, "source_any": null, "type_of_any": 1}}}, "committed_datetime": {".class": "SymbolTableNode", "kind": "Mdef", "node": {".class": "Decorator", "func": {".class": "FuncDef", "arg_kinds": [0], "arg_names": ["self"], "flags": ["is_property", "is_decorated"], "fullname": "git.objects.commit.Commit.committed_datetime", "name": "committed_datetime", "type": null}, "is_overload": false, "var": {".class": "Var", "flags": ["is_initialized_in_class", "is_property", "is_ready"], "fullname": null, "name": "committed_datetime", "type": {".class": "CallableType", "arg_kinds": [0], "arg_names": ["self"], "arg_types": ["git.objects.commit.Commit"], "bound_args": [], "def_extras": {}, "fallback": "builtins.function", "implicit": true, "is_ellipsis_args": false, "name": "committed_datetime of Commit", "ret_type": {".class": "AnyType", "missing_import_name": null, "source_any": null, "type_of_any": 1}, "variables": []}}}}, "committer": {".class": "SymbolTableNode", "implicit": true, "kind": "Mdef", "node": {".class": "Var", "flags": [], "fullname": "git.objects.commit.Commit.committer", "name": "committer", "type": {".class": "AnyType", "missing_import_name": null, "source_any": null, "type_of_any": 1}}}, "committer_tz_offset": {".class": "SymbolTableNode", "implicit": true, "kind": "Mdef", "node": {".class": "Var", "flags": [], "fullname": "git.objects.commit.Commit.committer_tz_offset", "name": "committer_tz_offset", "type": {".class": "AnyType", "missing_import_name": null, "source_any": null, "type_of_any": 1}}}, "conf_encoding": {".class": "SymbolTableNode", "kind": "Mdef", "node": {".class": "Var", "flags": ["is_initialized_in_class", "is_ready"], "fullname": "git.objects.commit.Commit.conf_encoding", "name": "conf_encoding", "type": "builtins.str"}}, "count": {".class": "SymbolTableNode", "kind": "Mdef", "node": {".class": "FuncDef", "arg_kinds": [0, 1, 4], "arg_names": ["self", "paths", "kwargs"], "flags": [], "fullname": "git.objects.commit.Commit.count", "name": "count", "type": null}}, "create_from_tree": {".class": "SymbolTableNode", "kind": "Mdef", "node": {".class": "Decorator", "func": {".class": "FuncDef", "arg_kinds": [0, 0, 0, 0, 1, 1, 1, 1, 1, 1], "arg_names": ["cls", "repo", "tree", "message", "parent_commits", "head", "author", "committer", "author_date", "commit_date"], "flags": ["is_class", "is_decorated"], "fullname": "git.objects.commit.Commit.create_from_tree", "name": "create_from_tree", "type": null}, "is_overload": false, "var": {".class": "Var", "flags": ["is_initialized_in_class", "is_classmethod", "is_ready"], "fullname": null, "name": "create_from_tree", "type": {".class": "CallableType", "arg_kinds": [0, 0, 0, 0, 1, 1, 1, 1, 1, 1], "arg_names": ["cls", "repo", "tree", "message", "parent_commits", "head", "author", "committer", "author_date", "commit_date"], "arg_types": [{".class": "TypeType", "item": "git.objects.commit.Commit"}, {".class": "AnyType", "missing_import_name": null, "source_any": null, "type_of_any": 1}, {".class": "AnyType", "missing_import_name": null, "source_any": null, "type_of_any": 1}, {".class": "AnyType", "missing_import_name": null, "source_any": null, "type_of_any": 1}, {".class": "AnyType", "missing_import_name": null, "source_any": null, "type_of_any": 1}, {".class": "AnyType", "missing_import_name": null, "source_any": null, "type_of_any": 1}, {".class": "AnyType", "missing_import_name": null, "source_any": null, "type_of_any": 1}, {".class": "AnyType", "missing_import_name": null, "source_any": null, "type_of_any": 1}, {".class": "AnyType", "missing_import_name": null, "source_any": null, "type_of_any": 1}, {".class": "AnyType", "missing_import_name": null, "source_any": null, "type_of_any": 1}], "bound_args": [], "def_extras": {}, "fallback": "builtins.function", "implicit": true, "is_ellipsis_args": false, "name": "create_from_tree of Commit", "ret_type": {".class": "AnyType", "missing_import_name": null, "source_any": null, "type_of_any": 1}, "variables": []}}}}, "default_encoding": {".class": "SymbolTableNode", "kind": "Mdef", "node": {".class": "Var", "flags": ["is_initialized_in_class", "is_ready"], "fullname": "git.objects.commit.Commit.default_encoding", "name": "default_encoding", "type": "builtins.str"}}, "encoding": {".class": "SymbolTableNode", "implicit": true, "kind": "Mdef", "node": {".class": "Var", "flags": [], "fullname": "git.objects.commit.Commit.encoding", "name": "encoding", "type": {".class": "AnyType", "missing_import_name": null, "source_any": null, "type_of_any": 1}}}, "env_author_date": {".class": "SymbolTableNode", "kind": "Mdef", "node": {".class": "Var", "flags": ["is_initialized_in_class", "is_ready"], "fullname": "git.objects.commit.Commit.env_author_date", "name": "env_author_date", "type": "builtins.str"}}, "env_committer_date": {".class": "SymbolTableNode", "kind": "Mdef", "node": {".class": "Var", "flags": ["is_initialized_in_class", "is_ready"], "fullname": "git.objects.commit.Commit.env_committer_date", "name": "env_committer_date", "type": "builtins.str"}}, "gpgsig": {".class": "SymbolTableNode", "implicit": true, "kind": "Mdef", "node": {".class": "Var", "flags": [], "fullname": "git.objects.commit.Commit.gpgsig", "name": "gpgsig", "type": {".class": "AnyType", "missing_import_name": null, "source_any": null, "type_of_any": 1}}}, "iter_items": {".class": "SymbolTableNode", "kind": "Mdef", "node": {".class": "Decorator", "func": {".class": "FuncDef", "arg_kinds": [0, 0, 0, 1, 4], "arg_names": ["cls", "repo", "rev", "paths", "kwargs"], "flags": ["is_class", "is_decorated"], "fullname": "git.objects.commit.Commit.iter_items", "name": "iter_items", "type": null}, "is_overload": false, "var": {".class": "Var", "flags": ["is_initialized_in_class", "is_classmethod", "is_ready"], "fullname": null, "name": "iter_items", "type": {".class": "CallableType", "arg_kinds": [0, 0, 0, 1, 4], "arg_names": ["cls", "repo", "rev", "paths", "kwargs"], "arg_types": [{".class": "TypeType", "item": "git.objects.commit.Commit"}, {".class": "AnyType", "missing_import_name": null, "source_any": null, "type_of_any": 1}, {".class": "AnyType", "missing_import_name": null, "source_any": null, "type_of_any": 1}, {".class": "AnyType", "missing_import_name": null, "source_any": null, "type_of_any": 1}, {".class": "AnyType", "missing_import_name": null, "source_any": null, "type_of_any": 1}], "bound_args": [], "def_extras": {}, "fallback": "builtins.function", "implicit": true, "is_ellipsis_args": false, "name": "iter_items of Commit", "ret_type": {".class": "AnyType", "missing_import_name": null, "source_any": null, "type_of_any": 1}, "variables": []}}}}, "iter_parents": {".class": "SymbolTableNode", "kind": "Mdef", "node": {".class": "FuncDef", "arg_kinds": [0, 1, 4], "arg_names": ["self", "paths", "kwargs"], "flags": [], "fullname": "git.objects.commit.Commit.iter_parents", "name": "iter_parents", "type": null}}, "message": {".class": "SymbolTableNode", "implicit": true, "kind": "Mdef", "node": {".class": "Var", "flags": [], "fullname": "git.objects.commit.Commit.message", "name": "message", "type": {".class": "AnyType", "missing_import_name": null, "source_any": null, "type_of_any": 1}}}, "name_rev": {".class": "SymbolTableNode", "kind": "Mdef", "node": {".class": "Decorator", "func": {".class": "FuncDef", "arg_kinds": [0], "arg_names": ["self"], "flags": ["is_property", "is_decorated"], "fullname": "git.objects.commit.Commit.name_rev", "name": "name_rev", "type": null}, "is_overload": false, "var": {".class": "Var", "flags": ["is_initialized_in_class", "is_property", "is_ready"], "fullname": null, "name": "name_rev", "type": {".class": "CallableType", "arg_kinds": [0], "arg_names": ["self"], "arg_types": ["git.objects.commit.Commit"], "bound_args": [], "def_extras": {}, "fallback": "builtins.function", "implicit": true, "is_ellipsis_args": false, "name": "name_rev of Commit", "ret_type": {".class": "AnyType", "missing_import_name": null, "source_any": null, "type_of_any": 1}, "variables": []}}}}, "parents": {".class": "SymbolTableNode", "implicit": true, "kind": "Mdef", "node": {".class": "Var", "flags": [], "fullname": "git.objects.commit.Commit.parents", "name": "parents", "type": {".class": "AnyType", "missing_import_name": null, "source_any": null, "type_of_any": 1}}}, "replace": {".class": "SymbolTableNode", "kind": "Mdef", "node": {".class": "FuncDef", "arg_kinds": [0, 4], "arg_names": ["self", "kwargs"], "flags": [], "fullname": "git.objects.commit.Commit.replace", "name": "replace", "type": null}}, "stats": {".class": "SymbolTableNode", "kind": "Mdef", "node": {".class": "Decorator", "func": {".class": "FuncDef", "arg_kinds": [0], "arg_names": ["self"], "flags": ["is_property", "is_decorated"], "fullname": "git.objects.commit.Commit.stats", "name": "stats", "type": null}, "is_overload": false, "var": {".class": "Var", "flags": ["is_initialized_in_class", "is_property", "is_ready"], "fullname": null, "name": "stats", "type": {".class": "CallableType", "arg_kinds": [0], "arg_names": ["self"], "arg_types": ["git.objects.commit.Commit"], "bound_args": [], "def_extras": {}, "fallback": "builtins.function", "implicit": true, "is_ellipsis_args": false, "name": "stats of Commit", "ret_type": {".class": "AnyType", "missing_import_name": null, "source_any": null, "type_of_any": 1}, "variables": []}}}}, "summary": {".class": "SymbolTableNode", "kind": "Mdef", "node": {".class": "Decorator", "func": {".class": "FuncDef", "arg_kinds": [0], "arg_names": ["self"], "flags": ["is_property", "is_decorated"], "fullname": "git.objects.commit.Commit.summary", "name": "summary", "type": null}, "is_overload": false, "var": {".class": "Var", "flags": ["is_initialized_in_class", "is_property", "is_ready"], "fullname": null, "name": "summary", "type": {".class": "CallableType", "arg_kinds": [0], "arg_names": ["self"], "arg_types": ["git.objects.commit.Commit"], "bound_args": [], "def_extras": {}, "fallback": "builtins.function", "implicit": true, "is_ellipsis_args": false, "name": "summary of Commit", "ret_type": {".class": "AnyType", "missing_import_name": null, "source_any": null, "type_of_any": 1}, "variables": []}}}}, "tree": {".class": "SymbolTableNode", "implicit": true, "kind": "Mdef", "node": {".class": "Var", "flags": [], "fullname": "git.objects.commit.Commit.tree", "name": "tree", "type": {".class": "AnyType", "missing_import_name": null, "source_any": null, "type_of_any": 1}}}, "type": {".class": "SymbolTableNode", "kind": "Mdef", "node": {".class": "Var", "flags": ["is_initialized_in_class", "is_ready"], "fullname": "git.objects.commit.Commit.type", "name": "type", "type": "builtins.str"}}}, "tuple_type": null, "type_vars": [], "typeddict_type": null}}, "Diffable": {".class": "SymbolTableNode", "cross_ref": "git.diff.Diffable", "kind": "Gdef", "module_public": false}, "IStream": {".class": "SymbolTableNode", "kind": "Gdef", "module_public": false, "node": {".class": "Var", "flags": ["is_suppressed_import", "is_ready"], "fullname": "git.objects.commit.IStream", "name": "IStream", "type": {".class": "AnyType", "missing_import_name": "git.objects.commit.IStream", "source_any": null, "type_of_any": 3}}}, "Iterable": {".class": "SymbolTableNode", "cross_ref": "git.util.Iterable", "kind": "Gdef", "module_public": false}, "Serializable": {".class": "SymbolTableNode", "cross_ref": "git.objects.util.Serializable", "kind": "Gdef", "module_public": false}, "Stats": {".class": "SymbolTableNode", "cross_ref": "git.util.Stats", "kind": "Gdef", "module_public": false}, "Traversable": {".class": "SymbolTableNode", "cross_ref": "git.objects.util.Traversable", "kind": "Gdef", "module_public": false}, "Tree": {".class": "SymbolTableNode", "cross_ref": "git.objects.tree.Tree", "kind": "Gdef", "module_public": false}, "__all__": {".class": "SymbolTableNode", "kind": "Gdef", "module_public": false, "node": {".class": "Var", "flags": [], "fullname": "git.objects.commit.__all__", "name": "__all__", "type": {".class": "TupleType", "implicit": false, "items": ["builtins.str"], "partial_fallback": {".class": "Instance", "args": [{".class": "AnyType", "missing_import_name": null, "source_any": null, "type_of_any": 6}], "type_ref": "builtins.tuple"}}}}, "__doc__": {".class": "SymbolTableNode", "kind": "Gdef", "module_public": false, "node": {".class": "Var", "flags": ["is_ready"], "fullname": "git.objects.commit.__doc__", "name": "__doc__", "type": "builtins.str"}}, "__file__": {".class": "SymbolTableNode", "kind": "Gdef", "module_public": false, "node": {".class": "Var", "flags": ["is_ready"], "fullname": "git.objects.commit.__file__", "name": "__file__", "type": "builtins.str"}}, "__name__": {".class": "SymbolTableNode", "kind": "Gdef", "module_public": false, "node": {".class": "Var", "flags": ["is_ready"], "fullname": "git.objects.commit.__name__", "name": "__name__", "type": "builtins.str"}}, "__package__": {".class": "SymbolTableNode", "kind": "Gdef", "module_public": false, "node": {".class": "Var", "flags": ["is_ready"], "fullname": "git.objects.commit.__package__", "name": "__package__", "type": "builtins.str"}}, "altz_to_utctz_str": {".class": "SymbolTableNode", "cross_ref": "git.objects.util.altz_to_utctz_str", "kind": "Gdef", "module_public": false}, "altzone": {".class": "SymbolTableNode", "cross_ref": "time.altzone", "kind": "Gdef", "module_public": false}, "base": {".class": "SymbolTableNode", "cross_ref": "git.objects.base", "kind": "Gdef", "module_public": false}, "daylight": {".class": "SymbolTableNode", "cross_ref": "time.daylight", "kind": "Gdef", "module_public": false}, "finalize_process": {".class": "SymbolTableNode", "cross_ref": "git.util.finalize_process", "kind": "Gdef", "module_public": false}, "from_timestamp": {".class": "SymbolTableNode", "cross_ref": "git.objects.util.from_timestamp", "kind": "Gdef", "module_public": false}, "hex_to_bin": {".class": "SymbolTableNode", "cross_ref": "git.util.hex_to_bin", "kind": "Gdef", "module_public": false}, "localtime": {".class": "SymbolTableNode", "cross_ref": "time.localtime", "kind": "Gdef", "module_public": false}, "log": {".class": "SymbolTableNode", "kind": "Gdef", "module_public": false, "node": {".class": "Var", "flags": [], "fullname": "git.objects.commit.log", "name": "log", "type": "logging.Logger"}}, "logging": {".class": "SymbolTableNode", "cross_ref": "logging", "kind": "Gdef", "module_public": false}, "os": {".class": "SymbolTableNode", "cross_ref": "os", "kind": "Gdef", "module_public": false}, "parse_actor_and_date": {".class": "SymbolTableNode", "cross_ref": "git.objects.util.parse_actor_and_date", "kind": "Gdef", "module_public": false}, "parse_date": {".class": "SymbolTableNode", "cross_ref": "git.objects.util.parse_date", "kind": "Gdef", "module_public": false}, "time": {".class": "SymbolTableNode", "cross_ref": "time.time", "kind": "Gdef", "module_public": false}, "timezone": {".class": "SymbolTableNode", "cross_ref": "time.timezone", "kind": "Gdef", "module_public": false}}, "path": "c:\\dev\\GitPython\\git\\objects\\commit.py"}